archdash/__init__.py
archdash/app.py
archdash/clientside_callbacks.py
archdash/constants.py
archdash/examples.py
archdash/layout.py
archdash/models.py
archdash/session_graph.py
archdash/setup.py
archdash/assets/modern_style.css
archdash/assets/tab-sid.js
archdash-1.1.0.dist-info/licenses/LICENSE
archdash-1.1.0.dist-info/METADATA
archdash-1.1.0.dist-info/WHEEL
archdash-1.1.0.dist-info/entry_points.txt
archdash-1.1.0.dist-info/top_level.txt
archdash-1.1.0.dist-info/RECORD
