Metadata-Version: 2.4
Name: archdash
Version: 1.1.0
Summary: A powerful architectural calculation tool for building and analyzing complex calculation graphs
Home-page: https://github.com/Readm/ArchDash
Author: Your Name
Author-email: Your Name <your.email@example.com>
License: MIT
Project-URL: Homepage, https://github.com/Readm/ArchDash
Project-URL: Repository, https://github.com/Readm/ArchDash
Project-URL: Issues, https://github.com/Readm/ArchDash/issues
Project-URL: Documentation, https://github.com/Readm/ArchDash/blob/main/README.md
Classifier: Development Status :: 4 - Beta
Classifier: Intended Audience :: Developers
Classifier: Intended Audience :: Science/Research
Classifier: License :: OSI Approved :: MIT License
Classifier: Operating System :: OS Independent
Classifier: Programming Language :: Python :: 3
Classifier: Programming Language :: Python :: 3.8
Classifier: Programming Language :: Python :: 3.9
Classifier: Programming Language :: Python :: 3.10
Classifier: Programming Language :: Python :: 3.11
Classifier: Topic :: Scientific/Engineering
Classifier: Topic :: Software Development :: Libraries :: Python Modules
Classifier: Framework :: Dash
Requires-Python: >=3.8
License-File: LICENSE
Requires-Dist: dash>=2.0.0
Requires-Dist: dash-bootstrap-components==2.0.3
Requires-Dist: dash-ace
Requires-Dist: pandas>=1.0.0
Requires-Dist: plotly>=5.0.0
Requires-Dist: numpy>=1.20.0
Provides-Extra: dev
Requires-Dist: pytest>=7.0.0; extra == "dev"
Requires-Dist: pytest-cov>=4.0.0; extra == "dev"
Requires-Dist: pytest-xdist>=3.0.0; extra == "dev"
Requires-Dist: selenium>=4.0.0; extra == "dev"
Dynamic: author
Dynamic: home-page
Dynamic: license-file
Dynamic: requires-python
